spond/__init__.py
spond/_event_template.py
spond/base.py
spond/club.py
spond/spond.py
spond-1.1.1.dist-info/LICENSE
spond-1.1.1.dist-info/METADATA
spond-1.1.1.dist-info/WHEEL
spond-1.1.1.dist-info/RECORD
