Metadata-Version: 2.3
Name: spond
Version: 1.1.1
Summary: Simple, unofficial library with some example scripts to access data from the Spond API.
License: GPL 3.0
Author: Ola Thoresen
Author-email: ola@nytt.no
Requires-Python: >=3.9,<4.0
Classifier: License :: Other/Proprietary License
Classifier: Programming Language :: Python :: 3
Classifier: Programming Language :: Python :: 3.9
Classifier: Programming Language :: Python :: 3.10
Classifier: Programming Language :: Python :: 3.11
Classifier: Programming Language :: Python :: 3.12
Classifier: Programming Language :: Python :: 3.13
Requires-Dist: aiohttp (>=3.8.5,<4.0.0)
Project-URL: Repository, https://github.com/Olen/Spond
